rerun_robotics/__init__.py
rerun_robotics/franka_panda.py
rerun_robotics/rerun_urdf.py
rerun_robotics/utils.py
rerun_robotics-0.0.7.dist-info/LICENSE
rerun_robotics-0.0.7.dist-info/METADATA
rerun_robotics-0.0.7.dist-info/WHEEL
rerun_robotics-0.0.7.dist-info/top_level.txt
rerun_robotics-0.0.7.dist-info/RECORD
