Metadata-Version: 2.1
Name: rerun-robotics
Version: 0.0.7
Summary: Robotics visualization using Rerun
Author-email: William Shen <willshen@mit.edu>
License:                                    MIT License
Project-URL: Source, https://github.com/williamshen-nz/rerun-robotics
Keywords: robotics,visualization
Classifier: License :: OSI Approved :: MIT License
Classifier: Programming Language :: Python :: 3
Requires-Python: >=3.8
License-File: LICENSE
Requires-Dist: numpy
Requires-Dist: pybullet
Requires-Dist: rerun-sdk>=0.18.0
Requires-Dist: trimesh
Requires-Dist: tqdm
Requires-Dist: yourdfpy
Provides-Extra: dev
Requires-Dist: black; extra == "dev"
Requires-Dist: isort; extra == "dev"
